otcclient/__init__.py
otcclient/shell.py
otcclient/bin/__init__.py
otcclient/core/OtcConfig.py
otcclient/core/__init__.py
otcclient/core/argmanager.py
otcclient/core/configloader.py
otcclient/core/otcpluginbase.py
otcclient/core/otcpluginbase_py2.py
otcclient/core/otcpluginbase_py3.py
otcclient/core/pluginmanager.py
otcclient/core/userconfigaction.py
otcclient/plugins/__init__.py
otcclient/plugins/Json/Json.py
otcclient/plugins/Json/__init__.py
otcclient/plugins/Json/templates/__init__.py
otcclient/plugins/autoscaling/__init__.py
otcclient/plugins/autoscaling/autoscaling.py
otcclient/plugins/autoscaling/templates/__init__.py
otcclient/plugins/autoscaling/templates/batch_delete_AS_config.template
otcclient/plugins/autoscaling/templates/batch_remove_add_instance.template
otcclient/plugins/autoscaling/templates/create_as_configuration.template
otcclient/plugins/autoscaling/templates/create_as_group.template
otcclient/plugins/autoscaling/templates/create_as_policy.template
otcclient/plugins/autoscaling/templates/disable_enable_as_group.template
otcclient/plugins/autoscaling/templates/execute_enable_disable_as_policy.template
otcclient/plugins/autoscaling/templates/modify_as_group.template
otcclient/plugins/autoscaling/templates/modify_as_policy.template
otcclient/plugins/cce/__init__.py
otcclient/plugins/cce/cce.py
otcclient/plugins/cce/templates/__init__.py
otcclient/plugins/cce/templates/cce_add_node.template
otcclient/plugins/cce/templates/cce_create_cluster.template
otcclient/plugins/cce/templates/cce_create_endpoint.template
otcclient/plugins/cce/templates/cce_create_pod.template
otcclient/plugins/cce/templates/cce_create_pod_template.template
otcclient/plugins/cce/templates/cce_create_rc.template
otcclient/plugins/cce/templates/cce_create_secret.template
otcclient/plugins/cce/templates/cce_create_service.template
otcclient/plugins/cce/templates/cce_rename_namespace.template
python_otcclient-0.3.65.dist-info/DESCRIPTION.rst
python_otcclient-0.3.65.dist-info/METADATA
python_otcclient-0.3.65.dist-info/RECORD
python_otcclient-0.3.65.dist-info/WHEEL
python_otcclient-0.3.65.dist-info/entry_points.txt
python_otcclient-0.3.65.dist-info/metadata.json
python_otcclient-0.3.65.dist-info/top_level.txt
python_otcclient-0.3.65.dist-info/zip-safe
