Metadata-Version: 2.0
Name: python-otcclient
Version: 0.3.65
Summary: Open Telecom Client Tool
Home-page: https://github.com/OpenTelekomCloud/python-otcclient
Author: Zsolt Nagy
Author-email: Z.Nagy@t-systems.com
License: MIT License
Keywords: otc,openstack,huawei,cloud,devops,t-systems,s3,obs,containers,docker,rds
Platform: UNKNOWN
Classifier: Development Status :: 6 - Mature
Classifier: Intended Audience :: Developers
Classifier: Intended Audience :: Science/Research
Classifier: License :: OSI Approved :: MIT License
Classifier: Programming Language :: Python
Classifier: Topic :: Software Development :: Libraries :: Python Modules
Requires-Dist: boto3>=1.3.0
Requires-Dist: prettytable>=0.7.0
Requires-Dist: requests>=2.10.0
Requires-Dist: jmespath>=0.7.1,<1.0.0
Requires-Dist: Jinja2>=2.7
